ki_aws_strands_agentcore_mcp_server/__init__.py
ki_aws_strands_agentcore_mcp_server/main.py
ki_aws_strands_agentcore_mcp_server-0.1.4.dist-info/METADATA
ki_aws_strands_agentcore_mcp_server-0.1.4.dist-info/WHEEL
ki_aws_strands_agentcore_mcp_server-0.1.4.dist-info/entry_points.txt
ki_aws_strands_agentcore_mcp_server-0.1.4.dist-info/top_level.txt
ki_aws_strands_agentcore_mcp_server-0.1.4.dist-info/RECORD
