Metadata-Version: 2.4
Name: ki-aws-strands-agentcore-mcp-server
Version: 0.1.4
Summary: MCP server for Strands Agent to Bedrock AgentCore workflow automation
Author-email: Ki <ki@example.com>
License-Expression: MIT
Project-URL: Homepage, https://github.com/ki/ki-aws-strands-agentcore-mcp-server
Project-URL: Repository, https://github.com/ki/ki-aws-strands-agentcore-mcp-server
Requires-Python: >=3.10
Requires-Dist: mcp>=0.8.0.dev0
Requires-Dist: fastmcp>=0.1.0
Requires-Dist: strands-agents>=0.1.0
Requires-Dist: strands-agents-tools>=0.1.0
Requires-Dist: bedrock-agentcore>=0.1.0
Requires-Dist: bedrock-agentcore-starter-toolkit>=0.1.0
